my_bittle/__init__.py
my_bittle/bittle_keyboard_control.py
my_bittle/bittle_serial_controller.py
my_bittle/keyboard_listener.py
my_bittle-0.0.4.dist-info/LICENSE
my_bittle-0.0.4.dist-info/METADATA
my_bittle-0.0.4.dist-info/WHEEL
my_bittle-0.0.4.dist-info/entry_points.txt
my_bittle-0.0.4.dist-info/top_level.txt
my_bittle-0.0.4.dist-info/RECORD
