Metadata-Version: 2.1
Name: my-bittle
Version: 0.0.4
Summary: A small package to enable keyboard control of the Bittle robot dog.
Author-email: MZandtheRaspberryPi <mzandtheraspberrypi@gmail.com>
Project-URL: Homepage, https://github.com/MZandtheRaspberryPi/my_bittle
Classifier: Programming Language :: Python :: 3
Classifier: License :: OSI Approved :: MIT License
Classifier: Operating System :: OS Independent
Requires-Python: >=3.6
License-File: LICENSE
Requires-Dist: pyserial
